{
    "name": "exp-reload",
    "description": "Live browser reload plugin for Expansive",
    "version": "0.3.0",
    "keywords": [
        "expansive-plugin",
        "reload"
    ],
    "licenses": "GPL",
    "repository": {
        "type": "git",
        "url": "git://github.com/embedthis/exp-reload.git"
    },
    "dependencies": {
        "jquery": "~3"
    },
    "devDependencies": {
        "expansive": ">=0.7.0",
        "pak": ">=0.11.3"
    },
    "export": [
        {
            "from": [
                "partials/**",
                "contents/**"
            ],
            "to": "${CONTENTS}/.."
        },
        {
            "from": "*.js.exp",
            "to": "exp-reload"
        }
    ],
    "origin": "embedthis/exp-reload"
}
